chaukas/py.typed
chaukas/spec/__init__.py
chaukas/spec/common/__init__.py
chaukas/spec/common/v1/__init__.py
chaukas/spec/common/v1/events_pb2.py
chaukas/spec/common/v1/events_pb2.pyi
chaukas/spec/common/v1/events_pb2_grpc.py
chaukas/spec/common/v1/query_pb2.py
chaukas/spec/common/v1/query_pb2.pyi
chaukas/spec/common/v1/query_pb2_grpc.py
chaukas/spec/server/__init__.py
chaukas/spec/server/v1/__init__.py
chaukas/spec/server/v1/server_pb2.py
chaukas/spec/server/v1/server_pb2.pyi
chaukas/spec/server/v1/server_pb2_grpc.py
chaukas_spec_server-1.0.4.dist-info/licenses/LICENSE
chaukas_spec_server-1.0.4.dist-info/METADATA
chaukas_spec_server-1.0.4.dist-info/WHEEL
chaukas_spec_server-1.0.4.dist-info/top_level.txt
chaukas_spec_server-1.0.4.dist-info/RECORD
